vicops_api/__init__.py
vicops_api/main.py
vicops_api-1.1.1.dist-info/LICENSE
vicops_api-1.1.1.dist-info/METADATA
vicops_api-1.1.1.dist-info/WHEEL
vicops_api-1.1.1.dist-info/RECORD
